{
    "type": "FeatureCollection",
    "features": [
        {
            "type": "Feature",
            "geometry": {
                "type": "Point",
                "coordinates": [
                    -6.2380987,
                    54.7214649,
                    0
                ]
            },
            "properties": {
                "name": "Castlewood Tree Top Adventure",
                "styleUrl": "#icon-1899-0288D1-nodesc",
                "styleHash": "48999a20",
                "styleMapHash": {
                    "normal": "#icon-1899-0288D1-nodesc-normal",
                    "highlight": "#icon-1899-0288D1-nodesc-highlight"
                },
                "icon": "https://www.gstatic.com/mapspro/images/stock/503-wht-blank_maps.png"
            }
        },
        {
            "type": "Feature",
            "geometry": {
                "type": "Point",
                "coordinates": [
                    -5.9873267,
                    54.5733828,
                    0
                ]
            },
            "properties": {
                "name": "Andersonstown Leisure Centre",
                "styleUrl": "#icon-1899-0288D1-nodesc",
                "styleHash": "48999a20",
                "styleMapHash": {
                    "normal": "#icon-1899-0288D1-nodesc-normal",
                    "highlight": "#icon-1899-0288D1-nodesc-highlight"
                },
                "icon": "https://www.gstatic.com/mapspro/images/stock/503-wht-blank_maps.png"
            }
        },
        {
            "type": "Feature",
            "geometry": {
                "type": "Point",
                "coordinates": [
                    -6.0409336,
                    54.5002315,
                    0
                ]
            },
            "properties": {
                "name": "High Rise - Family Adventure Centre Lisburn",
                "styleUrl": "#icon-1899-0288D1-nodesc",
                "styleHash": "48999a20",
                "styleMapHash": {
                    "normal": "#icon-1899-0288D1-nodesc-normal",
                    "highlight": "#icon-1899-0288D1-nodesc-highlight"
                },
                "icon": "https://www.gstatic.com/mapspro/images/stock/503-wht-blank_maps.png"
            }
        }
    ]
}