{
    "type": "FeatureCollection",
    "features": [
        {
            "type": "Feature",
            "geometry": {
                "type": "Point",
                "coordinates": [
                    -5.9561663,
                    54.9661652,
                    0
                ]
            },
            "properties": {
                "name": "Glenarm Castle",
                "styleUrl": "#icon-1899-0288D1-nodesc",
                "styleHash": "48999a20",
                "styleMapHash": {
                    "normal": "#icon-1899-0288D1-nodesc-normal",
                    "highlight": "#icon-1899-0288D1-nodesc-highlight"
                },
                "icon": "https://www.gstatic.com/mapspro/images/stock/503-wht-blank_maps.png"
            }
        },
        {
            "type": "Feature",
            "geometry": {
                "type": "Point",
                "coordinates": [
                    -5.9155104,
                    54.6047336,
                    0
                ]
            },
            "properties": {
                "name": "W5",
                "styleUrl": "#icon-1899-0288D1-nodesc",
                "styleHash": "48999a20",
                "styleMapHash": {
                    "normal": "#icon-1899-0288D1-nodesc-normal",
                    "highlight": "#icon-1899-0288D1-nodesc-highlight"
                },
                "icon": "https://www.gstatic.com/mapspro/images/stock/503-wht-blank_maps.png"
            }
        }
    ]
}